{
  "name": "Session50 Test User",
  "blood_type": "AB-",
  "allergies": [
    "Sulfa drugs"
  ],
  "medical_conditions": [
    "Mild asthma"
  ],
  "medications": [
    "WORKFLOW_MED"
  ],
  "emergency_contacts": [
    {
      "name": "Emergency Mom",
      "phone": "+1-555-123-4567",
      "relationship": "Mother"
    }
  ],
  "notes": "",
  "updated_at": "2026-01-12T03:47:21.674Z",
  "baseline_vitals": {
    "heart_rate": 72,
    "spo2": 98,
    "temperature": 36.7,
    "blood_pressure_systolic": null,
    "blood_pressure_diastolic": null,
    "recorded_at": "2026-01-09T11:27:25.554Z"
  }
}